gem_assist/__init__.py
gem_assist/core.py
gem_botist-0.1.0.dist-info/METADATA
gem_botist-0.1.0.dist-info/WHEEL
gem_botist-0.1.0.dist-info/top_level.txt
gem_botist-0.1.0.dist-info/RECORD
