Metadata-Version: 2.4
Name: gem-botist
Version: 0.1.0
Summary: A helper library for AI processing using Google Gemini.
Author-email: Sharvin <sharvinvincent9100@gmail.com>
